arggo/__init__.py
arggo/arggo.py
arggo/dataclass_utils.py
arggo/integrations.py
arggo/logger.py
arggo/parser.py
arggo/_internal/__init__.py
arggo/_internal/global_store.py
arggo/environment/__init__.py
arggo/environment/workdir.py
arggo/types/__init__.py
arggo/types/enums.py
arggo-0.0.3.dist-info/LICENSE.md
arggo-0.0.3.dist-info/METADATA
arggo-0.0.3.dist-info/WHEEL
arggo-0.0.3.dist-info/top_level.txt
arggo-0.0.3.dist-info/RECORD
