Metadata-Version: 2.1
Name: arggo
Version: 0.0.3
Summary: The no-brainer package for setting up python experiments
Home-page: https://github.com/mikimn/arggo
Author: Miki Mendelson-Mints
Author-email: mikimn1999@gmail.com
License: UNKNOWN
Project-URL: Bug Tracker, https://github.com/mikimn/arggo/issues
Platform: UNKNOWN
Classifier: Programming Language :: Python :: 3
Classifier: License :: OSI Approved :: MIT License
Classifier: Operating System :: OS Independent
Requires-Python: >=3.7
